Sumeet_Library_1/Sumeet_Library_1.py
Sumeet_Library_1/__init__.py
Sumeet_Library_1-0.1.dist-info/METADATA
Sumeet_Library_1-0.1.dist-info/WHEEL
Sumeet_Library_1-0.1.dist-info/top_level.txt
Sumeet_Library_1-0.1.dist-info/RECORD
