Metadata-Version: 2.1
Name: Sumeet-Library-1
Version: 0.1
Summary: First One
Author: Sumeet Mitra
